gumloop/__init__.py
gumloop/client.py
gumloop-0.1.0.dist-info/METADATA
gumloop-0.1.0.dist-info/WHEEL
gumloop-0.1.0.dist-info/licenses/LICENSE
gumloop-0.1.0.dist-info/RECORD
