Metadata-Version: 2.4
Name: gumloop
Version: 0.1.0
Summary: Python client for the Gumloop API
Project-URL: Homepage, https://github.com/gumloop/gumloop-py
Project-URL: Bug Tracker, https://github.com/gumloop/gumloop-py/issues
Author-email: Rahul Behal <rahul@gumloop.com>
License-File: LICENSE
Classifier: License :: OSI Approved :: Apache Software License
Classifier: Operating System :: OS Independent
Classifier: Programming Language :: Python :: 3
Requires-Python: >=3.7
Requires-Dist: requests>=2.25.0
